alumath/__init__.py
alumath/matrix.py
alumath/operations.py
alumathGroup26-0.1.1.dist-info/METADATA
alumathGroup26-0.1.1.dist-info/WHEEL
alumathGroup26-0.1.1.dist-info/top_level.txt
alumathGroup26-0.1.1.dist-info/RECORD
