Metadata-Version: 2.1
Name: alumathGroup26
Version: 0.1.1
Summary: A simple matrix calculator library
Home-page: https://github.com/lGikundiro/Advanced-Linear-Algebra---Formative-2
Author: Terry Manzi
Author-email: Manzi Terry <m.terry@alustudent.com>
License: MIT
Project-URL: Homepage, https://github.com/lGikundiro/Advanced-Linear-Algebra---Formative-2
Project-URL: Repository, https://github.com/lGikundiro/Advanced-Linear-Algebra---Formative-2
Keywords: matrix,mathematics,linear algebra,calculator
Classifier: Development Status :: 3 - Alpha
Classifier: Intended Audience :: Developers
Classifier: License :: OSI Approved :: MIT License
Classifier: Operating System :: OS Independent
Classifier: Programming Language :: Python :: 3
Requires-Python: >=3.7
